dolfyn/__init__.py
dolfyn/_version.py
dolfyn/binned.py
dolfyn/time.py
dolfyn/velocity.py
dolfyn/adp/__init__.py
dolfyn/adp/api.py
dolfyn/adp/clean.py
dolfyn/adp/turbulence.py
dolfyn/adv/__init__.py
dolfyn/adv/api.py
dolfyn/adv/clean.py
dolfyn/adv/motion.py
dolfyn/adv/turbulence.py
dolfyn/example_data/__init__.py
dolfyn/io/__init__.py
dolfyn/io/api.py
dolfyn/io/base.py
dolfyn/io/nortek.py
dolfyn/io/nortek2.py
dolfyn/io/nortek2_defs.py
dolfyn/io/nortek2_lib.py
dolfyn/io/nortek_defs.py
dolfyn/io/rdi.py
dolfyn/io/rdi_defs.py
dolfyn/io/rdi_lib.py
dolfyn/rotate/__init__.py
dolfyn/rotate/api.py
dolfyn/rotate/awac.py
dolfyn/rotate/base.py
dolfyn/rotate/rdi.py
dolfyn/rotate/signature.py
dolfyn/rotate/vector.py
dolfyn/tools/__init__.py
dolfyn/tools/misc.py
dolfyn/tools/psd.py
dolfyn-1.3.0.data/scripts/binary2mat.py
dolfyn-1.3.0.data/scripts/motcorrect_vector.py
dolfyn-1.3.0.dist-info/LICENSE.txt
dolfyn-1.3.0.dist-info/METADATA
dolfyn-1.3.0.dist-info/WHEEL
dolfyn-1.3.0.dist-info/top_level.txt
dolfyn-1.3.0.dist-info/RECORD
